drip/__init__.py
drip/client.py
drip/core.py
drip/errors.py
drip/models.py
drip/resilience.py
drip/stream.py
drip/utils.py
drip/integrations/__init__.py
drip/integrations/langchain.py
drip/middleware/__init__.py
drip/middleware/core.py
drip/middleware/fastapi.py
drip/middleware/flask.py
drip/middleware/types.py
drip_sdk-1.1.0.dist-info/METADATA
drip_sdk-1.1.0.dist-info/WHEEL
drip_sdk-1.1.0.dist-info/licenses/LICENSE
drip_sdk-1.1.0.dist-info/RECORD
