Metadata-Version: 2.4
Name: drip-sdk
Version: 1.1.0
Summary: Official Python SDK for Drip - usage-based billing infrastructure with on-chain settlement
Project-URL: Homepage, https://drip.dev
Project-URL: Documentation, https://docs.drip.dev
Project-URL: Repository, https://github.com/drip/sdk-python
Author-email: Drip <sdk@drip.dev>
License-Expression: MIT
License-File: LICENSE
Keywords: api,billing,blockchain,drip,metered-billing,payments,sdk,usage-based
Classifier: Development Status :: 4 - Beta
Classifier: Intended Audience :: Developers
Classifier: License :: OSI Approved :: MIT License
Classifier: Operating System :: OS Independent
Classifier: Programming Language :: Python :: 3
Classifier: Programming Language :: Python :: 3.10
Classifier: Programming Language :: Python :: 3.11
Classifier: Programming Language :: Python :: 3.12
Classifier: Typing :: Typed
Requires-Python: >=3.10
Requires-Dist: httpx>=0.25.0
Requires-Dist: pydantic>=2.0.0
Provides-Extra: all
Requires-Dist: fastapi>=0.100.0; extra == 'all'
Requires-Dist: flask>=2.0.0; extra == 'all'
Requires-Dist: langchain-core>=0.1.0; extra == 'all'
Requires-Dist: starlette>=0.27.0; extra == 'all'
Provides-Extra: dev
Requires-Dist: mypy>=1.0.0; extra == 'dev'
Requires-Dist: pytest-asyncio>=0.21.0; extra == 'dev'
Requires-Dist: pytest-cov>=4.0.0; extra == 'dev'
Requires-Dist: pytest>=7.0.0; extra == 'dev'
Requires-Dist: respx>=0.20.0; extra == 'dev'
Requires-Dist: ruff>=0.1.0; extra == 'dev'
Provides-Extra: fastapi
Requires-Dist: fastapi>=0.100.0; extra == 'fastapi'
Requires-Dist: starlette>=0.27.0; extra == 'fastapi'
Provides-Extra: flask
Requires-Dist: flask>=2.0.0; extra == 'flask'
Provides-Extra: langchain
Requires-Dist: langchain-core>=0.1.0; extra == 'langchain'
